sparklightautoml/__init__.py
sparklightautoml/automl/__init__.py
sparklightautoml/automl/base.py
sparklightautoml/automl/blend.py
sparklightautoml/automl/presets/__init__.py
sparklightautoml/automl/presets/base.py
sparklightautoml/automl/presets/tabular_config.yml
sparklightautoml/automl/presets/tabular_presets.py
sparklightautoml/automl/presets/utils.py
sparklightautoml/computations/__init__.py
sparklightautoml/computations/base.py
sparklightautoml/computations/builder.py
sparklightautoml/computations/parallel.py
sparklightautoml/computations/sequential.py
sparklightautoml/computations/utils.py
sparklightautoml/dataset/__init__.py
sparklightautoml/dataset/base.py
sparklightautoml/dataset/persistence.py
sparklightautoml/dataset/roles.py
sparklightautoml/ml_algo/__init__.py
sparklightautoml/ml_algo/base.py
sparklightautoml/ml_algo/boost_lgbm.py
sparklightautoml/ml_algo/linear_pyspark.py
sparklightautoml/ml_algo/tuning/__init__.py
sparklightautoml/ml_algo/tuning/parallel_optuna.py
sparklightautoml/mlwriters.py
sparklightautoml/pipelines/__init__.py
sparklightautoml/pipelines/base.py
sparklightautoml/pipelines/features/__init__.py
sparklightautoml/pipelines/features/base.py
sparklightautoml/pipelines/features/lgb_pipeline.py
sparklightautoml/pipelines/features/linear_pipeline.py
sparklightautoml/pipelines/ml/__init__.py
sparklightautoml/pipelines/ml/base.py
sparklightautoml/pipelines/ml/nested_ml_pipe.py
sparklightautoml/pipelines/selection/__init__.py
sparklightautoml/pipelines/selection/base.py
sparklightautoml/pipelines/selection/permutation_importance_based.py
sparklightautoml/reader/__init__.py
sparklightautoml/reader/base.py
sparklightautoml/reader/guess_roles.py
sparklightautoml/report/__init__.py
sparklightautoml/report/handy_spark_utils.py
sparklightautoml/report/report_deco.py
sparklightautoml/report/spark_report_templates/binary_inference_section.html
sparklightautoml/report/spark_report_templates/feature_importance_section.html
sparklightautoml-0.5.0.dist-info/LICENSE
sparklightautoml-0.5.0.dist-info/WHEEL
sparklightautoml-0.5.0.dist-info/METADATA
sparklightautoml-0.5.0.dist-info/RECORD
